excitertools.py
excitertools-2025.0.1.dist-info/LICENSE
excitertools-2025.0.1.dist-info/METADATA
excitertools-2025.0.1.dist-info/WHEEL
excitertools-2025.0.1.dist-info/top_level.txt
excitertools-2025.0.1.dist-info/RECORD
